django_heaven/__init__.py
django_heaven/asgi.py
django_heaven/settings.py
django_heaven/urls.py
django_heaven/wsgi.py
responses/__init__.py
responses/base.py
responses/http.py
responses/json.py
responses/redirect.py
responses/rest_framework.py
responses/tests/__init__.py
responses/tests/base.py
responses/tests/test_json.py
services/base.py
services/decorators.py
services/exceptions.py
services/users.py
django_heaven-0.0.2.dist-info/LICENSE.rst
django_heaven-0.0.2.dist-info/METADATA
django_heaven-0.0.2.dist-info/WHEEL
django_heaven-0.0.2.dist-info/top_level.txt
django_heaven-0.0.2.dist-info/RECORD
